kiteprotocol/__init__.py
kiteprotocol/kite_protocol.py
kiteprotocol/utils.py
protocol/__init__.py
protocol/kite_protocol.py
protocol/utils.py
uilib/__init__.py
uilib/alert_msg_dialog.py
uilib/captcha_form.py
uilib/login_form.py
uilib/main_form.py
github_kite-0.0.6.dist-info/METADATA
github_kite-0.0.6.dist-info/WHEEL
github_kite-0.0.6.dist-info/top_level.txt
github_kite-0.0.6.dist-info/RECORD
