Metadata-Version: 2.1
Name: github-kite
Version: 0.0.6
Summary: github test proj
Home-page: https://github.com/test/test
Author: author no body
Author-email: Shive.shell@gmail.com
License: UNKNOWN
Platform: UNKNOWN
Classifier: Programming Language :: Python :: 3
Classifier: License :: OSI Approved :: MIT License
Classifier: Operating System :: OS Independent
Requires-Python: >=3.7
Requires-Dist: requests
Requires-Dist: websocket-client
Requires-Dist: netifaces
